HerdingCats/__init__.py
HerdingCats/data_loader/__init__.py
HerdingCats/data_loader/data_loader.py
HerdingCats/endpoints/__init__.py
HerdingCats/endpoints/api_endpoints.py
HerdingCats/errors/__init__.py
HerdingCats/errors/cats_errors.py
HerdingCats/explorer/__init__.py
HerdingCats/explorer/cat_explore.py
HerdingCats/session/__init__.py
HerdingCats/session/cat_session.py
herdingcats-0.1.7.dist-info/METADATA
herdingcats-0.1.7.dist-info/WHEEL
herdingcats-0.1.7.dist-info/RECORD
